{
    "anims": [
        {
            "key": "left",
            "type": "frames",
            "repeat": -1,
            "frameRate": 12,
            "frames": [
                {
                    "key": "late_run1",
                    "frame": "lrun_l_1_tmp",
                    "evnt": []
                },
                {
                    "key": "late_run1",
                    "frame": "lrun_l_3_tmp",
                    "evnt": []
                },
                {
                    "key": "late_run1",
                    "frame": "lrun_l_5_tmp",
                    "evnt": []
                },
                {
                    "key": "late_run1",
                    "frame": "lrun_l_7_tmp",
                    "evnt": []
                },
                {
                    "key": "late_run1",
                    "frame": "lrun_l_9_tmp",
                    "evnt": []
                },
                {
                    "key": "late_run1",
                    "frame": "lrun_l_11_tmp",
                    "evnt": []
                },
                {
                    "key": "late_run1",
                    "frame": "lrun_l_13_tmp",
                    "evnt": []
                },
                {
                    "key": "late_run1",
                    "frame": "lrun_l_15_tmp",
                    "evnt": []
                }
            ]
        },
        {
            "key": "downright",
            "type": "frames",
            "repeat": -1,
            "frameRate": 12,
            "frames": [
                {
                    "key": "late_run1",
                    "frame": "lrun_dr_1_tmp",
                    "evnt": []
                },
                {
                    "key": "late_run1",
                    "frame": "lrun_dr_3_tmp",
                    "evnt": []
                },
                {
                    "key": "late_run1",
                    "frame": "lrun_dr_5_tmp",
                    "evnt": []
                },
                {
                    "key": "late_run1",
                    "frame": "lrun_dr_7_tmp",
                    "evnt": []
                },
                {
                    "key": "late_run1",
                    "frame": "lrun_dr_9_tmp",
                    "evnt": []
                },
                {
                    "key": "late_run1",
                    "frame": "lrun_dr_11_tmp",
                    "evnt": []
                },
                {
                    "key": "late_run1",
                    "frame": "lrun_dr_13_tmp",
                    "evnt": []
                },
                {
                    "key": "late_run1",
                    "frame": "lrun_dr_15_tmp",
                    "evnt": []
                }
            ]
        },
        {
            "key": "downleft",
            "type": "frames",
            "repeat": -1,
            "frameRate": 12,
            "frames": [
                {
                    "key": "late_run1",
                    "frame": "lrun_dl_1_tmp",
                    "evnt": []
                },
                {
                    "key": "late_run1",
                    "frame": "lrun_dl_3_tmp",
                    "evnt": []
                },
                {
                    "key": "late_run1",
                    "frame": "lrun_dl_5_tmp",
                    "evnt": []
                },
                {
                    "key": "late_run1",
                    "frame": "lrun_dl_7_tmp",
                    "evnt": []
                },
                {
                    "key": "late_run1",
                    "frame": "lrun_dl_9_tmp",
                    "evnt": []
                },
                {
                    "key": "late_run1",
                    "frame": "lrun_dl_11_tmp",
                    "evnt": []
                },
                {
                    "key": "late_run1",
                    "frame": "lrun_dl_13_tmp",
                    "evnt": []
                },
                {
                    "key": "late_run1",
                    "frame": "lrun_dl_15_tmp",
                    "evnt": []
                }
            ]
        },
        {
            "key": "down",
            "type": "frames",
            "repeat": -1,
            "frameRate": 12,
            "frames": [
                {
                    "key": "late_run1",
                    "frame": "lrun_d_1_tmp",
                    "evnt": []
                },
                {
                    "key": "late_run1",
                    "frame": "lrun_d_3_tmp",
                    "evnt": []
                },
                {
                    "key": "late_run1",
                    "frame": "lrun_d_5_tmp",
                    "evnt": []
                },
                {
                    "key": "late_run1",
                    "frame": "lrun_d_7_tmp",
                    "evnt": []
                },
                {
                    "key": "late_run1",
                    "frame": "lrun_d_9_tmp",
                    "evnt": []
                },
                {
                    "key": "late_run1",
                    "frame": "lrun_d_11_tmp",
                    "evnt": []
                },
                {
                    "key": "late_run1",
                    "frame": "lrun_d_13_tmp",
                    "evnt": []
                },
                {
                    "key": "late_run1",
                    "frame": "lrun_d_15_tmp",
                    "evnt": []
                }
            ]
        }
    ]
}